Metadata-Version: 1.0
Name: sendEmail198
Version: 0.2
Summary: A setup test package
Home-page: https://github.com/8613AQ7/sendEmail198
Author: UNKNOWN
Author-email: UNKNOWN
License: UNKNOWN
Keywords: email,simple
Platform: UNKNOWN
